arcgeo/__init__.py
arcgeo/arcgeo.py
arcgeo/common.py
arcgeo-0.0.4.dist-info/LICENSE
arcgeo-0.0.4.dist-info/METADATA
arcgeo-0.0.4.dist-info/WHEEL
arcgeo-0.0.4.dist-info/entry_points.txt
arcgeo-0.0.4.dist-info/top_level.txt
arcgeo-0.0.4.dist-info/RECORD
